lib/__init__.py
lib/db_connection.py
lib/top_display.py
lib/top_monitor.py
lib/top_realtime.py
lib/cache_manager/__init__.py
lib/cache_manager/cache_manager.py
lib/cli/__init__.py
lib/cli/analyze_command.py
lib/cli/cache_command.py
lib/cli/configuration_wizard.py
lib/cli/howdoi_command.py
lib/cli/init_command.py
lib/cli/interactive_mode.py
lib/cli/output_formatter.py
lib/cli/parameter_prompt.py
lib/cli/query_command.py
lib/cli/rdst_cli.py
lib/cli/rdstdbg_command.py
lib/cli/readyset_setup.py
lib/cli/report_command.py
lib/cli/run_workflow.py
lib/cli/schema_command.py
lib/cli/top.py
lib/data_manager/__init__.py
lib/data_manager/data_manager.py
lib/data_manager_service/__init__.py
lib/data_manager_service/data_manager_service.py
lib/data_manager_service/data_manager_service_command_sets.py
lib/data_structures/__init__.py
lib/data_structures/query_defaults.py
lib/data_structures/semantic_layer.py
lib/debug/__init__.py
lib/debug/formatters.py
lib/debug/llm_inspector.py
lib/debug/session_inspector.py
lib/debug/snapshot_browser.py
lib/debug/state_viewer.py
lib/engines/ask3/__init__.py
lib/engines/ask3/agent.py
lib/engines/ask3/agent_context.py
lib/engines/ask3/agent_tools.py
lib/engines/ask3/clarification.py
lib/engines/ask3/context.py
lib/engines/ask3/engine.py
lib/engines/ask3/escalation.py
lib/engines/ask3/presenter.py
lib/engines/ask3/types.py
lib/engines/ask3/phases/__init__.py
lib/engines/ask3/phases/clarify.py
lib/engines/ask3/phases/execute.py
lib/engines/ask3/phases/expand.py
lib/engines/ask3/phases/filter.py
lib/engines/ask3/phases/generate.py
lib/engines/ask3/phases/present.py
lib/engines/ask3/phases/schema.py
lib/engines/ask3/phases/validate.py
lib/functions/__init__.py
lib/functions/ambiguity_detection.py
lib/functions/error_parser.py
lib/functions/explain_analysis.py
lib/functions/llm_analysis.py
lib/functions/parallel_merge.py
lib/functions/performance_comparison.py
lib/functions/query_metrics.py
lib/functions/query_parameterization.py
rdst_staging-0.1.149.dist-info/METADATA
rdst_staging-0.1.149.dist-info/WHEEL
rdst_staging-0.1.149.dist-info/entry_points.txt
rdst_staging-0.1.149.dist-info/RECORD
